pong/__init__.py
pong/components/Ball.py
pong/components/Controller.py
pong/components/Text.py
pong/components/__init__.py
pong/game/Basic.py
pong/game/__init__.py
pong/utility/__init__.py
pong/utility/colours.py
python_pong-1.0.2.dist-info/LICENSE
python_pong-1.0.2.dist-info/METADATA
python_pong-1.0.2.dist-info/WHEEL
python_pong-1.0.2.dist-info/top_level.txt
python_pong-1.0.2.dist-info/RECORD
