Metadata-Version: 2.1
Name: python-pong
Version: 1.0.2
Summary: A Python library for implementing Pong in Pygame.
Author: Dyrektrypt
License: MIT License
Project-URL: Repository, https://github.com/dyrektrypt/python-pong
Project-URL: Homepage, https://github.com/dyrektrypt/python-pong#readme
Project-URL: Bug Tracker, https://github.com/dyrektrypt/python-pong/issues
License-File: LICENSE
Requires-Dist: pygame >=2.5.1
